lebaronysard_first_package/__init__.py
lebaronysard_first_package/main.py
lebaronysard_first_package-0.1.1.dist-info/METADATA
lebaronysard_first_package-0.1.1.dist-info/WHEEL
lebaronysard_first_package-0.1.1.dist-info/entry_points.txt
lebaronysard_first_package-0.1.1.dist-info/top_level.txt
lebaronysard_first_package-0.1.1.dist-info/RECORD
