Metadata-Version: 2.2
Name: lebaronysard_first_package
Version: 0.1.1
Summary: A simple CLI package but an amazing one.
Requires-Dist: click==8.1.3
